<?xml version = "1.0"?>
<data simType = "WatorWorldSimulation">
    <settings>
        <title>watorworld 1</title>
        <author>group14</author>
        <generatorType>quota</generatorType>
        <cellShape>Hexagon</cellShape>
        <gridShape>HexagonalGrid</gridShape>
        <rows>60</rows>
        <columns>60</columns>
        <speed>10</speed>
        <startEnergy>5</startEnergy>
        <sharkReproductionMax>20</sharkReproductionMax>
        <fishReproductionMax>5</fishReproductionMax>
        <energyGain>5</energyGain>
        <sharkRate>20</sharkRate>
        <fishRate>1000</fishRate>
    </settings>

    <grid>
        <row>
            <Cell cellType = "FishCell">
                <reproductionTime>5</reproductionTime>`
            </Cell>
            <Cell cellType = "EmptyCell"></Cell>
            <Cell cellType = "EmptyCell"></Cell>
            <Cell cellType = "EmptyCell"></Cell>
            <Cell cellType = "EmptyCell"></Cell>
            <Cell cellType = "EmptyCell"></Cell>
            <Cell cellType = "FishCell">
                <reproductionTime>5</reproductionTime>`
            </Cell>
            <Cell cellType = "EmptyCell"></Cell>
            <Cell cellType = "EmptyCell"></Cell>
            <Cell cellType = "EmptyCell"></Cell>
            <Cell cellType = "EmptyCell"></Cell>
            <Cell cellType = "EmptyCell"></Cell>
        </row>
        <row>
            <Cell cellType = "EmptyCell"></Cell>
            <Cell cellType = "EmptyCell"></Cell>
            <Cell cellType = "FishCell">
                <reproductionTime>5</reproductionTime>`
            </Cell>
            <Cell cellType = "EmptyCell"></Cell>
            <Cell cellType = "EmptyCell"></Cell>
            <Cell cellType = "EmptyCell"></Cell>
            <Cell cellType = "FishCell">
                <reproductionTime>5</reproductionTime>`
            </Cell>
            <Cell cellType = "EmptyCell"></Cell>
            <Cell cellType = "EmptyCell"></Cell>
            <Cell cellType = "EmptyCell"></Cell>
            <Cell cellType = "EmptyCell"></Cell>
            <Cell cellType = "EmptyCell"></Cell>
        </row>
        <row>
            <Cell cellType = "EmptyCell"></Cell>
            <Cell cellType = "EmptyCell"></Cell>
            <Cell cellType = "EmptyCell"></Cell>
            <Cell cellType = "FishCell">
                <reproductionTime>5</reproductionTime>`
            </Cell>
            <Cell cellType = "EmptyCell"></Cell>
            <Cell cellType = "FishCell">
                <reproductionTime>5</reproductionTime>`
            </Cell>
            <Cell cellType = "EmptyCell"></Cell>
            <Cell cellType = "FishCell">
                <reproductionTime>5</reproductionTime>`
            </Cell>
            <Cell cellType = "EmptyCell"></Cell>
            <Cell cellType = "EmptyCell"></Cell>
            <Cell cellType = "EmptyCell"></Cell>
            <Cell cellType = "EmptyCell"></Cell>
        </row>
        <row>
            <Cell cellType = "FishCell">
                <reproductionTime>5</reproductionTime>`
            </Cell>
            <Cell cellType = "FishCell">
                <reproductionTime>5</reproductionTime>`
            </Cell>
            <Cell cellType = "EmptyCell"></Cell>
            <Cell cellType = "EmptyCell"></Cell>
            <Cell cellType = "EmptyCell"></Cell>
            <Cell cellType = "FishCell">
                <reproductionTime>5</reproductionTime>`
            </Cell>
            <Cell cellType = "EmptyCell"></Cell>
            <Cell cellType = "EmptyCell"></Cell>
            <Cell cellType = "EmptyCell"></Cell>
            <Cell cellType = "EmptyCell"></Cell>
            <Cell cellType = "EmptyCell"></Cell>
            <Cell cellType = "FishCell">
                <reproductionTime>5</reproductionTime>`
            </Cell>
        </row>
        <row>
            <Cell cellType = "EmptyCell"></Cell>
            <Cell cellType = "EmptyCell"></Cell>
            <Cell cellType = "EmptyCell"></Cell>
            <Cell cellType = "EmptyCell"></Cell>
            <Cell cellType = "EmptyCell"></Cell>
            <Cell cellType = "EmptyCell"></Cell>
            <Cell cellType = "EmptyCell"></Cell>
            <Cell cellType = "FishCell">
                <reproductionTime>5</reproductionTime>`
            </Cell>
            <Cell cellType = "EmptyCell"></Cell>
            <Cell cellType = "EmptyCell"></Cell>
            <Cell cellType = "EmptyCell"></Cell>
            <Cell cellType = "EmptyCell"></Cell>
        </row>
        <row>
            <Cell cellType = "EmptyCell"></Cell>
            <Cell cellType = "EmptyCell"></Cell>
            <Cell cellType = "EmptyCell"></Cell>
            <Cell cellType = "EmptyCell"></Cell>
            <Cell cellType = "EmptyCell"></Cell>
            <Cell cellType = "FishCell">
                <reproductionTime>5</reproductionTime>`
            </Cell>
            <Cell cellType = "EmptyCell"></Cell>
            <Cell cellType = "EmptyCell"></Cell>
            <Cell cellType = "EmptyCell"></Cell>
            <Cell cellType = "EmptyCell"></Cell>
            <Cell cellType = "EmptyCell"></Cell>
            <Cell cellType = "EmptyCell"></Cell>
        </row>
        <row>
            <Cell cellType = "FishCell">
                <reproductionTime>5</reproductionTime>`
            </Cell>
            <Cell cellType = "EmptyCell"></Cell>
            <Cell cellType = "EmptyCell"></Cell>
            <Cell cellType = "EmptyCell"></Cell>
            <Cell cellType = "EmptyCell"></Cell>
            <Cell cellType = "FishCell">
                <reproductionTime>5</reproductionTime>`
            </Cell>
            <Cell cellType = "EmptyCell"></Cell>
            <Cell cellType = "EmptyCell"></Cell>
            <Cell cellType = "EmptyCell"></Cell>
            <Cell cellType = "EmptyCell"></Cell>
            <Cell cellType = "EmptyCell"></Cell>
            <Cell cellType = "EmptyCell"></Cell>
        </row>
        <row>
            <Cell cellType = "EmptyCell"></Cell>
            <Cell cellType = "EmptyCell"></Cell>
            <Cell cellType = "EmptyCell"></Cell>
            <Cell cellType = "EmptyCell"></Cell>
            <Cell cellType = "FishCell">
                <reproductionTime>5</reproductionTime>`
            </Cell>
            <Cell cellType = "EmptyCell"></Cell>
            <Cell cellType = "EmptyCell"></Cell>
            <Cell cellType = "SharkCell">
                <reproductionTime>5</reproductionTime>
                <energy>10</energy>
                <energyGain>10</energyGain>
            </Cell>
            <Cell cellType = "EmptyCell"></Cell>
            <Cell cellType = "EmptyCell"></Cell>
            <Cell cellType = "EmptyCell"></Cell>
            <Cell cellType = "EmptyCell"></Cell>
        </row>
        <row>
            <Cell cellType = "EmptyCell"></Cell>
            <Cell cellType = "EmptyCell"></Cell>
            <Cell cellType = "EmptyCell"></Cell>
            <Cell cellType = "FishCell">
                <reproductionTime>5</reproductionTime>`
            </Cell>
            <Cell cellType = "EmptyCell"></Cell>
            <Cell cellType = "EmptyCell"></Cell>
            <Cell cellType = "EmptyCell"></Cell>
            <Cell cellType = "EmptyCell"></Cell>
            <Cell cellType = "EmptyCell"></Cell>
            <Cell cellType = "EmptyCell"></Cell>
            <Cell cellType = "EmptyCell"></Cell>
            <Cell cellType = "EmptyCell"></Cell>
        </row>
        <row>
            <Cell cellType = "EmptyCell"></Cell>
            <Cell cellType = "EmptyCell"></Cell>
            <Cell cellType = "EmptyCell"></Cell>
            <Cell cellType = "EmptyCell"></Cell>
            <Cell cellType = "EmptyCell"></Cell>
            <Cell cellType = "EmptyCell"></Cell>
            <Cell cellType = "EmptyCell"></Cell>
            <Cell cellType = "EmptyCell"></Cell>
            <Cell cellType = "EmptyCell"></Cell>
            <Cell cellType = "EmptyCell"></Cell>
            <Cell cellType = "EmptyCell"></Cell>
            <Cell cellType = "EmptyCell"></Cell>
        </row>
        <row>
            <Cell cellType = "EmptyCell"></Cell>
            <Cell cellType = "EmptyCell"></Cell>
            <Cell cellType = "EmptyCell"></Cell>
            <Cell cellType = "EmptyCell"></Cell>
            <Cell cellType = "EmptyCell"></Cell>
            <Cell cellType = "EmptyCell"></Cell>
            <Cell cellType = "EmptyCell"></Cell>
            <Cell cellType = "SharkCell">
                <reproductionTime>5</reproductionTime>
                <energy>10</energy>
                <energyGain>10</energyGain>
            </Cell>
            <Cell cellType = "EmptyCell"></Cell>
            <Cell cellType = "EmptyCell"></Cell>
            <Cell cellType = "EmptyCell"></Cell>
            <Cell cellType = "EmptyCell"></Cell>
        </row>
        <row>
            <Cell cellType = "EmptyCell"></Cell>
            <Cell cellType = "EmptyCell"></Cell>
            <Cell cellType = "FishCell">
                <reproductionTime>5</reproductionTime>`
            </Cell>
            <Cell cellType = "EmptyCell"></Cell>
            <Cell cellType = "EmptyCell"></Cell>
            <Cell cellType = "EmptyCell"></Cell>
            <Cell cellType = "EmptyCell"></Cell>
            <Cell cellType = "FishCell">
                <reproductionTime>5</reproductionTime>`
            </Cell>
            <Cell cellType = "EmptyCell"></Cell>
            <Cell cellType = "EmptyCell"></Cell>
            <Cell cellType = "FishCell">
                <reproductionTime>5</reproductionTime>`
            </Cell>
            <Cell cellType = "EmptyCell"></Cell>
        </row>
    </grid>
</data>